chatosaurus_embedder-0.1.0.dist-info/licenses/LICENSE
embed_providers/__init__.py
embed_providers/base_embedder.py
embed_providers/factory.py
embed_providers/openai_embedder.py
utils/__init__.py
utils/api_communication.py
utils/file_loader.py
utils/json_saver.py
chatosaurus_embedder-0.1.0.dist-info/METADATA
chatosaurus_embedder-0.1.0.dist-info/WHEEL
chatosaurus_embedder-0.1.0.dist-info/entry_points.txt
chatosaurus_embedder-0.1.0.dist-info/top_level.txt
chatosaurus_embedder-0.1.0.dist-info/RECORD
