Metadata-Version: 2.4
Name: chatosaurus-embedder
Version: 0.1.0
Summary: Embedding generator for Chatosaurus documentation
Author: The Dino Stack
License: MIT
Classifier: Programming Language :: Python :: 3
Classifier: License :: OSI Approved :: MIT License
Classifier: Operating System :: OS Independent
Requires-Python: >=3.8
License-File: LICENSE
Dynamic: author
Dynamic: classifier
Dynamic: license
Dynamic: license-file
Dynamic: requires-python
Dynamic: summary
